daglib/__init__.py
daglib/dag.py
daglib/task.py
daglib-0.5.0.dist-info/LICENSE
daglib-0.5.0.dist-info/WHEEL
daglib-0.5.0.dist-info/METADATA
daglib-0.5.0.dist-info/RECORD
