Metadata-Version: 2.1
Name: daglib
Version: 0.5.0
Summary: Lightweight DAG composition framework
Home-page: https://github.com/mharrisb1/daglib
License: MIT
Author: Michael Harris
Author-email: mharris@luabase.com
Requires-Python: >=3.10,<4.0
Classifier: Intended Audience :: Developers
Classifier: License :: OSI Approved :: MIT License
Classifier: Programming Language :: Python :: 3
Classifier: Programming Language :: Python :: 3.10
Provides-Extra: graphviz
Provides-Extra: ipycytoscape
Requires-Dist: dask[delayed] (>=2022.7.1,<2023.0.0)
Requires-Dist: graphviz (>=0.20,<0.21); extra == "graphviz"
Requires-Dist: ipycytoscape (>=1.3.3,<2.0.0); extra == "ipycytoscape"
Requires-Dist: networkx (>=2.8.5,<3.0.0)
Project-URL: Documentation, https://mharrisb1.github.io/daglib/
Project-URL: Repository, https://github.com/mharrisb1/daglib
